{"name":"build-javascript","namedChunkGroups":{"polyfill":{"name":"polyfill","assets":[{"name":"webpack-runtime-d16735df36b4c0712223.js","size":5334},{"name":"polyfill-4aa291e7e6681714b3e8.js","size":85818}],"filteredAssets":0,"assetsSize":91152,"filteredAuxiliaryAssets":2,"auxiliaryAssetsSize":228160},"app":{"name":"app","assets":[{"name":"webpack-runtime-d16735df36b4c0712223.js","size":5334},{"name":"framework-c9b92197cbae3c33e091.js","size":149065},{"name":"app-c321c5efdf12999a1dd7.js","size":124066}],"filteredAssets":0,"assetsSize":278465,"filteredAuxiliaryAssets":3,"auxiliaryAssetsSize":813413},"component---src-components-templates-log-js":{"name":"component---src-components-templates-log-js","assets":[{"name":"styles.202b843a3255cda52de9.css","size":14743},{"name":"cb1608f2-e929cbbe07b150a1b5f2.js","size":2003},{"name":"a9a7754c-2b4e2c0ca6bd7326a683.js","size":2518},{"name":"commons-265bcd9e70c63b7db7d3.js","size":67659},{"name":"component---src-components-templates-log-js-8be2b192cec9967ef4ea.js","size":9606}],"filteredAssets":0,"assetsSize":96529,"filteredAuxiliaryAssets":4,"auxiliaryAssetsSize":2021948},"component---src-components-templates-post-js":{"name":"component---src-components-templates-post-js","assets":[{"name":"styles.202b843a3255cda52de9.css","size":14743},{"name":"cb1608f2-e929cbbe07b150a1b5f2.js","size":2003},{"name":"a9a7754c-2b4e2c0ca6bd7326a683.js","size":2518},{"name":"commons-265bcd9e70c63b7db7d3.js","size":67659},{"name":"6f273c79816dfb4b70a43ea8273d765ababe6227-4330a1d1022bb393ff3f.js","size":9505},{"name":"component---src-components-templates-post-js-d80014afc9ad124b5ee3.js","size":106522}],"filteredAssets":0,"assetsSize":202950,"filteredAuxiliaryAssets":5,"auxiliaryAssetsSize":2487580},"component---src-pages-404-js":{"name":"component---src-pages-404-js","assets":[{"name":"styles.202b843a3255cda52de9.css","size":14743},{"name":"cb1608f2-e929cbbe07b150a1b5f2.js","size":2003},{"name":"a9a7754c-2b4e2c0ca6bd7326a683.js","size":2518},{"name":"commons-265bcd9e70c63b7db7d3.js","size":67659},{"name":"component---src-pages-404-js-5ed0d86fb0763a04a4b4.js","size":507}],"filteredAssets":0,"assetsSize":87430,"filteredAuxiliaryAssets":4,"auxiliaryAssetsSize":1992487},"component---src-pages-index-js":{"name":"component---src-pages-index-js","assets":[{"name":"styles.202b843a3255cda52de9.css","size":14743},{"name":"cb1608f2-e929cbbe07b150a1b5f2.js","size":2003},{"name":"a9a7754c-2b4e2c0ca6bd7326a683.js","size":2518},{"name":"commons-265bcd9e70c63b7db7d3.js","size":67659},{"name":"component---src-pages-index-js-67136b30be5717c21631.js","size":641}],"filteredAssets":0,"assetsSize":87564,"filteredAuxiliaryAssets":4,"auxiliaryAssetsSize":1992627},"component---src-pages-logs-index-js":{"name":"component---src-pages-logs-index-js","assets":[{"name":"styles.202b843a3255cda52de9.css","size":14743},{"name":"cb1608f2-e929cbbe07b150a1b5f2.js","size":2003},{"name":"a9a7754c-2b4e2c0ca6bd7326a683.js","size":2518},{"name":"commons-265bcd9e70c63b7db7d3.js","size":67659},{"name":"component---src-pages-logs-index-js-bf19e8f568991d11bb86.js","size":9963}],"filteredAssets":0,"assetsSize":96886,"filteredAuxiliaryAssets":4,"auxiliaryAssetsSize":2023248},"component---src-pages-posts-index-js":{"name":"component---src-pages-posts-index-js","assets":[{"name":"styles.202b843a3255cda52de9.css","size":14743},{"name":"cb1608f2-e929cbbe07b150a1b5f2.js","size":2003},{"name":"a9a7754c-2b4e2c0ca6bd7326a683.js","size":2518},{"name":"commons-265bcd9e70c63b7db7d3.js","size":67659},{"name":"6f273c79816dfb4b70a43ea8273d765ababe6227-4330a1d1022bb393ff3f.js","size":9505},{"name":"component---src-pages-posts-index-js-2779df3cf8aef25ec545.js","size":1327}],"filteredAssets":0,"assetsSize":97755,"filteredAuxiliaryAssets":5,"auxiliaryAssetsSize":2060314}},"assetsByChunkName":{"polyfill":["webpack-runtime-d16735df36b4c0712223.js","polyfill-4aa291e7e6681714b3e8.js"],"app":["webpack-runtime-d16735df36b4c0712223.js","framework-c9b92197cbae3c33e091.js","app-c321c5efdf12999a1dd7.js"],"component---src-components-templates-log-js":["styles.202b843a3255cda52de9.css","cb1608f2-e929cbbe07b150a1b5f2.js","a9a7754c-2b4e2c0ca6bd7326a683.js","commons-265bcd9e70c63b7db7d3.js","component---src-components-templates-log-js-8be2b192cec9967ef4ea.js"],"component---src-components-templates-post-js":["styles.202b843a3255cda52de9.css","cb1608f2-e929cbbe07b150a1b5f2.js","a9a7754c-2b4e2c0ca6bd7326a683.js","commons-265bcd9e70c63b7db7d3.js","6f273c79816dfb4b70a43ea8273d765ababe6227-4330a1d1022bb393ff3f.js","component---src-components-templates-post-js-d80014afc9ad124b5ee3.js"],"component---src-pages-404-js":["styles.202b843a3255cda52de9.css","cb1608f2-e929cbbe07b150a1b5f2.js","a9a7754c-2b4e2c0ca6bd7326a683.js","commons-265bcd9e70c63b7db7d3.js","component---src-pages-404-js-5ed0d86fb0763a04a4b4.js"],"component---src-pages-index-js":["styles.202b843a3255cda52de9.css","cb1608f2-e929cbbe07b150a1b5f2.js","a9a7754c-2b4e2c0ca6bd7326a683.js","commons-265bcd9e70c63b7db7d3.js","component---src-pages-index-js-67136b30be5717c21631.js"],"component---src-pages-logs-index-js":["styles.202b843a3255cda52de9.css","cb1608f2-e929cbbe07b150a1b5f2.js","a9a7754c-2b4e2c0ca6bd7326a683.js","commons-265bcd9e70c63b7db7d3.js","component---src-pages-logs-index-js-bf19e8f568991d11bb86.js"],"component---src-pages-posts-index-js":["styles.202b843a3255cda52de9.css","cb1608f2-e929cbbe07b150a1b5f2.js","a9a7754c-2b4e2c0ca6bd7326a683.js","commons-265bcd9e70c63b7db7d3.js","6f273c79816dfb4b70a43ea8273d765ababe6227-4330a1d1022bb393ff3f.js","component---src-pages-posts-index-js-2779df3cf8aef25ec545.js"]},"childAssetsByChunkName":{}}